topsis/__main__.py
topsis/csvTopsis.py
TOPSIS_Vikram_101803368-1.0.2.dist-info/METADATA
TOPSIS_Vikram_101803368-1.0.2.dist-info/WHEEL
TOPSIS_Vikram_101803368-1.0.2.dist-info/entry_points.txt
TOPSIS_Vikram_101803368-1.0.2.dist-info/top_level.txt
TOPSIS_Vikram_101803368-1.0.2.dist-info/RECORD
