Metadata-Version: 2.1
Name: TOPSIS-Vikram-101803368
Version: 1.0.2
Summary: Apply topsis to a dataset in a csv file
Home-page: https://github.com/sixthkrum/topsis
Author: Vikram Alagh
Author-email: valagh_be18@thapar.edu
License: MIT
Platform: UNKNOWN
Classifier: License :: OSI Approved :: MIT License
Classifier: Programming Language :: Python :: 3
Classifier: Programming Language :: Python :: 3.7
